{"text": " You're such a fuckin' hoe, I love it You're such a fuckin' hoe, I love it You're such a fuckin' hoe, I love it Your boyfriend is a dork, make love it I just pulled up in the ghost, fucked that bitch up out in London Then I fucked up on her cousin or her sister, I don't know nothin' And my niggas gettin' ignorant, like a lighter bitch, we ignorant All this water on my neck looked like I felt when I went fishin' Burned with diamonds on my bust, now ooh fuck, what's the time? Man, smoke perp sippin' drain, ooh fuck, she take lines You're such a fuckin' hoe, I love it You're such a fuckin' hoe, when the first time they ask you You want sparkling or steel? Are you tryna act like you was drinkin' sparkling water Before you came out here? You're such a fuckin' hoe, I'm a sick fuck, I like a quick fuck I'm a sick fuck, I like a quick fuck I'm a sick fuck, I like a quick fuck I'm a sick fuck, I like a quick fuck I'm a sick fuck, I like a quick fuck I like my dick suck, I buy you a sick truck I buy you some new tits, I get you the nip tuck How you start a family, the condom slipped up I'm a sick fuck, I'm inappropriate I like hearing stories, I like that hoe shit I wanna hear more shit, I like the hoe shit Send me some more shit, you trippin' hoe bitch You're such a fuckin' hoe, I love it You know they couldn't say the shit they wanted to say They had the fake orgasms and shit We can tell niggas today, hey, I wanna cum, motherfucker", "segments": [{"id": 0, "seek": 0, "start": 11.24, "end": 14.32, "text": " You're such a fuckin' hoe, I love it", "tokens": [50364, 509, 434, 1270, 257, 20022, 6, 19709, 11, 286, 959, 309, 51084], "temperature": 0.0, "avg_logprob": -0.34618132969118515, "compression_ratio": 1.9605263157894737, "no_speech_prob": 0.6998893022537231, "confidence": 0.688, "words": [{"text": "You're", "start": 11.24, "end": 11.26, "confidence": 0.345}, {"text": "such", "start": 11.26, "end": 11.82, "confidence": 0.699}, {"text": "a", "start": 11.82, "end": 12.1, "confidence": 0.996}, {"text": "fuckin'", "start": 12.1, "end": 12.88, "confidence": 0.652}, {"text": "hoe,", "start": 12.88, "end": 13.04, "confidence": 0.677}, {"text": "I", "start": 13.36, "end": 13.76, "confidence": 0.993}, {"text": "love", "start": 13.76, "end": 14.1, "confidence": 0.997}, {"text": "it", "start": 14.1, "end": 14.32, "confidence": 0.998}]}, {"id": 1, "seek": 0, "start": 15.74, "end": 19.0, "text": " You're such a fuckin' hoe, I love it", "tokens": [51084, 509, 434, 1270, 257, 20022, 6, 19709, 11, 286, 959, 309, 51312], "temperature": 0.0, "avg_logprob": -0.34618132969118515, "compression_ratio": 1.9605263157894737, "no_speech_prob": 0.6998893022537231, "confidence": 0.988, "words": [{"text": "You're", "start": 15.74, "end": 16.3, "confidence": 0.955}, {"text": "such", "start": 16.3, "end": 16.5, "confidence": 0.999}, {"text": "a", "start": 16.5, "end": 16.72, "confidence": 1.0}, {"text": "fuckin'", "start": 16.72, "end": 17.44, "confidence": 0.987}, {"text": "hoe,", "start": 17.44, "end": 17.72, "confidence": 0.998}, {"text": "I", "start": 18.22, "end": 18.38, "confidence": 0.999}, {"text": "love", "start": 18.38, "end": 18.74, "confidence": 1.0}, {"text": "it", "start": 18.74, "end": 19.0, "confidence": 1.0}]}, {"id": 2, "seek": 0, "start": 20.36, "end": 23.54, "text": " You're such a fuckin' hoe, I love it", "tokens": [51312, 509, 434, 1270, 257, 20022, 6, 19709, 11, 286, 959, 309, 51542], "temperature": 0.0, "avg_logprob": -0.34618132969118515, "compression_ratio": 1.9605263157894737, "no_speech_prob": 0.6998893022537231, "confidence": 0.993, "words": [{"text": "You're", "start": 20.36, "end": 20.92, "confidence": 0.974}, {"text": "such", "start": 20.92, "end": 21.18, "confidence": 1.0}, {"text": "a", "start": 21.18, "end": 21.28, "confidence": 1.0}, {"text": "fuckin'", "start": 21.28, "end": 22.12, "confidence": 0.994}, {"text": "hoe,", "start": 22.12, "end": 22.36, "confidence": 0.999}, {"text": "I", "start": 22.8, "end": 23.0, "confidence": 1.0}, {"text": "love", "start": 23.0, "end": 23.34, "confidence": 1.0}, {"text": "it", "start": 23.34, "end": 23.54, "confidence": 1.0}]}, {"id": 3, "seek": 0, "start": 24.94, "end": 28.2, "text": " Your boyfriend is a dork, make love it", "tokens": [51542, 2260, 11457, 307, 257, 274, 1284, 11, 652, 959, 309, 51776], "temperature": 0.0, "avg_logprob": -0.34618132969118515, "compression_ratio": 1.9605263157894737, "no_speech_prob": 0.6998893022537231, "confidence": 0.738, "words": [{"text": "Your", "start": 24.94, "end": 25.3, "confidence": 0.761}, {"text": "boyfriend", "start": 25.3, "end": 25.92, "confidence": 0.996}, {"text": "is", "start": 25.92, "end": 26.34, "confidence": 0.994}, {"text": "a", "start": 26.34, "end": 26.62, "confidence": 0.896}, {"text": "dork,", "start": 26.62, "end": 27.16, "confidence": 0.556}, {"text": "make", "start": 27.48, "end": 27.66, "confidence": 0.874}, {"text": "love", "start": 27.66, "end": 28.0, "confidence": 0.936}, {"text": "it", "start": 28.0, "end": 28.2, "confidence": 0.382}]}, {"id": 4, "seek": 2824, "start": 29.38, "end": 33.86, "text": " I just pulled up in the ghost, fucked that bitch up out in London", "tokens": [50364, 286, 445, 7373, 493, 294, 264, 8359, 11, 22518, 300, 11960, 493, 484, 294, 7042, 50642], "temperature": 0.0, "avg_logprob": -0.36220857075282503, "compression_ratio": 1.6092436974789917, "no_speech_prob": 0.06987283378839493, "confidence": 0.864, "words": [{"text": "I", "start": 29.38, "end": 29.64, "confidence": 0.952}, {"text": "just", "start": 29.64, "end": 29.92, "confidence": 0.992}, {"text": "pulled", "start": 29.92, "end": 30.26, "confidence": 0.983}, {"text": "up", "start": 30.26, "end": 30.64, "confidence": 0.998}, {"text": "in", "start": 30.64, "end": 30.94, "confidence": 0.993}, {"text": "the", "start": 30.94, "end": 31.22, "confidence": 0.923}, {"text": "ghost,", "start": 31.22, "end": 31.44, "confidence": 0.393}, {"text": "fucked", "start": 31.56, "end": 32.0, "confidence": 0.609}, {"text": "that", "start": 32.0, "end": 32.24, "confidence": 0.993}, {"text": "bitch", "start": 32.24, "end": 32.66, "confidence": 0.99}, {"text": "up", "start": 32.66, "end": 32.98, "confidence": 0.789}, {"text": "out", "start": 32.98, "end": 33.24, "confidence": 0.871}, {"text": "in", "start": 33.24, "end": 33.46, "confidence": 0.953}, {"text": "London", "start": 33.46, "end": 33.86, "confidence": 0.984}]}, {"id": 5, "seek": 2824, "start": 34.0, "end": 38.42, "text": " Then I fucked up on her cousin or her sister, I don't know nothin'", "tokens": [50642, 1396, 286, 22518, 493, 322, 720, 16207, 420, 720, 4892, 11, 286, 500, 380, 458, 47562, 6, 50872], "temperature": 0.0, "avg_logprob": -0.36220857075282503, "compression_ratio": 1.6092436974789917, "no_speech_prob": 0.06987283378839493, "confidence": 0.835, "words": [{"text": "Then", "start": 34.0, "end": 34.38, "confidence": 0.561}, {"text": "I", "start": 34.38, "end": 34.58, "confidence": 0.989}, {"text": "fucked", "start": 34.58, "end": 34.92, "confidence": 0.995}, {"text": "up", "start": 34.92, "end": 35.26, "confidence": 0.902}, {"text": "on", "start": 35.26, "end": 35.52, "confidence": 0.999}, {"text": "her", "start": 35.52, "end": 35.8, "confidence": 0.473}, {"text": "cousin", "start": 35.8, "end": 36.16, "confidence": 0.993}, {"text": "or", "start": 36.16, "end": 36.52, "confidence": 0.455}, {"text": "her", "start": 36.52, "end": 36.88, "confidence": 0.995}, {"text": "sister,", "start": 36.88, "end": 37.32, "confidence": 0.996}, {"text": "I", "start": 37.5, "end": 37.68, "confidence": 0.988}, {"text": "don't", "start": 37.68, "end": 37.82, "confidence": 0.979}, {"text": "know", "start": 37.82, "end": 38.04, "confidence": 0.993}, {"text": "nothin'", "start": 38.04, "end": 38.42, "confidence": 0.753}]}, {"id": 6, "seek": 2824, "start": 38.6, "end": 43.06, "text": " And my niggas gettin' ignorant, like a lighter bitch, we ignorant", "tokens": [50872, 400, 452, 297, 6249, 296, 34568, 6, 29374, 11, 411, 257, 11546, 11960, 11, 321, 29374, 51104], "temperature": 0.0, "avg_logprob": -0.36220857075282503, "compression_ratio": 1.6092436974789917, "no_speech_prob": 0.06987283378839493, "confidence": 0.908, "words": [{"text": "And", "start": 38.6, "end": 38.86, "confidence": 0.918}, {"text": "my", "start": 38.86, "end": 39.16, "confidence": 0.992}, {"text": "niggas", "start": 39.16, "end": 39.74, "confidence": 0.941}, {"text": "gettin'", "start": 39.74, "end": 40.28, "confidence": 0.841}, {"text": "ignorant,", "start": 40.28, "end": 40.76, "confidence": 0.996}, {"text": "like", "start": 41.0, "end": 41.26, "confidence": 0.959}, {"text": "a", "start": 41.26, "end": 41.6, "confidence": 0.983}, {"text": "lighter", "start": 41.6, "end": 41.92, "confidence": 0.924}, {"text": "bitch,", "start": 41.92, "end": 42.24, "confidence": 0.671}, {"text": "we", "start": 42.32, "end": 42.68, "confidence": 0.995}, {"text": "ignorant", "start": 42.68, "end": 43.06, "confidence": 0.83}]}, {"id": 7, "seek": 2824, "start": 43.28, "end": 47.84, "text": " All this water on my neck looked like I felt when I went fishin'", "tokens": [51104, 1057, 341, 1281, 322, 452, 6189, 2956, 411, 286, 2762, 562, 286, 1437, 3506, 259, 6, 51334], "temperature": 0.0, "avg_logprob": -0.36220857075282503, "compression_ratio": 1.6092436974789917, "no_speech_prob": 0.06987283378839493, "confidence": 0.872, "words": [{"text": "All", "start": 43.28, "end": 43.54, "confidence": 0.966}, {"text": "this", "start": 43.54, "end": 43.84, "confidence": 0.934}, {"text": "water", "start": 43.84, "end": 44.24, "confidence": 0.953}, {"text": "on", "start": 44.24, "end": 44.66, "confidence": 0.995}, {"text": "my", "start": 44.66, "end": 44.98, "confidence": 0.999}, {"text": "neck", "start": 44.98, "end": 45.2, "confidence": 0.951}, {"text": "looked", "start": 45.2, "end": 45.48, "confidence": 0.427}, {"text": "like", "start": 45.48, "end": 45.8, "confidence": 0.998}, {"text": "I", "start": 45.8, "end": 46.04, "confidence": 0.989}, {"text": "felt", "start": 46.04, "end": 46.32, "confidence": 0.625}, {"text": "when", "start": 46.32, "end": 46.66, "confidence": 0.984}, {"text": "I", "start": 46.66, "end": 46.94, "confidence": 0.993}, {"text": "went", "start": 46.94, "end": 47.16, "confidence": 0.991}, {"text": "fishin'", "start": 47.16, "end": 47.84, "confidence": 0.814}]}, {"id": 8, "seek": 2824, "start": 47.84, "end": 52.14, "text": " Burned with diamonds on my bust, now ooh fuck, what's the time?", "tokens": [51334, 18328, 292, 365, 22612, 322, 452, 19432, 11, 586, 17024, 3275, 11, 437, 311, 264, 565, 30, 51562], "temperature": 0.0, "avg_logprob": -0.36220857075282503, "compression_ratio": 1.6092436974789917, "no_speech_prob": 0.06987283378839493, "confidence": 0.648, "words": [{"text": "Burned", "start": 47.84, "end": 48.26, "confidence": 0.198}, {"text": "with", "start": 48.26, "end": 48.3, "confidence": 0.586}, {"text": "diamonds", "start": 48.3, "end": 48.9, "confidence": 0.993}, {"text": "on", "start": 48.9, "end": 49.3, "confidence": 0.995}, {"text": "my", "start": 49.3, "end": 49.54, "confidence": 0.998}, {"text": "bust,", "start": 49.54, "end": 49.76, "confidence": 0.726}, {"text": "now", "start": 49.96, "end": 50.1, "confidence": 0.94}, {"text": "ooh", "start": 50.1, "end": 50.56, "confidence": 0.439}, {"text": "fuck,", "start": 50.56, "end": 51.02, "confidence": 0.502}, {"text": "what's", "start": 51.28, "end": 51.68, "confidence": 0.98}, {"text": "the", "start": 51.68, "end": 51.9, "confidence": 0.997}, {"text": "time?", "start": 51.9, "end": 52.14, "confidence": 0.711}]}, {"id": 9, "seek": 2824, "start": 52.52, "end": 57.02, "text": " Man, smoke perp sippin' drain, ooh fuck, she take lines", "tokens": [51562, 2458, 11, 8439, 680, 79, 1511, 427, 259, 6, 12339, 11, 17024, 3275, 11, 750, 747, 3876, 51802], "temperature": 0.0, "avg_logprob": -0.36220857075282503, "compression_ratio": 1.6092436974789917, "no_speech_prob": 0.06987283378839493, "confidence": 0.677, "words": [{"text": "Man,", "start": 52.52, "end": 52.8, "confidence": 0.324}, {"text": "smoke", "start": 52.94, "end": 53.2, "confidence": 0.752}, {"text": "perp", "start": 53.2, "end": 53.66, "confidence": 0.404}, {"text": "sippin'", "start": 53.66, "end": 54.2, "confidence": 0.8}, {"text": "drain,", "start": 54.2, "end": 54.44, "confidence": 0.349}, {"text": "ooh", "start": 54.8, "end": 55.24, "confidence": 0.948}, {"text": "fuck,", "start": 55.24, "end": 55.58, "confidence": 0.986}, {"text": "she", "start": 55.86, "end": 56.16, "confidence": 0.996}, {"text": "take", "start": 56.16, "end": 56.6, "confidence": 0.952}, {"text": "lines", "start": 56.6, "end": 57.02, "confidence": 0.852}]}, {"id": 10, "seek": 5700, "start": 57.32, "end": 61.62, "text": " You're such a fuckin' hoe, I love it", "tokens": [50364, 509, 434, 1270, 257, 20022, 6, 19709, 11, 286, 959, 309, 50814], "temperature": 0.0, "avg_logprob": -0.25641467923023664, "compression_ratio": 2.40251572327044, "no_speech_prob": 0.14192061126232147, "confidence": 0.997, "words": [{"text": "You're", "start": 57.32, "end": 57.82, "confidence": 0.994}, {"text": "such", "start": 57.82, "end": 58.04, "confidence": 1.0}, {"text": "a", "start": 58.04, "end": 58.28, "confidence": 1.0}, {"text": "fuckin'", "start": 58.28, "end": 58.96, "confidence": 0.992}, {"text": "hoe,", "start": 58.96, "end": 59.42, "confidence": 0.996}, {"text": "I", "start": 59.74, "end": 59.9, "confidence": 1.0}, {"text": "love", "start": 59.9, "end": 60.28, "confidence": 1.0}, {"text": "it", "start": 60.28, "end": 61.62, "confidence": 1.0}]}, {"id": 11, "seek": 5700, "start": 66.44, "end": 70.43, "text": " You're such a fuckin' hoe, when the first time they ask you", "tokens": [50814, 509, 434, 1270, 257, 20022, 6, 19709, 11, 562, 264, 700, 565, 436, 1029, 291, 51026], "temperature": 0.0, "avg_logprob": -0.25641467923023664, "compression_ratio": 2.40251572327044, "no_speech_prob": 0.14192061126232147, "confidence": 0.926, "words": [{"text": "You're", "start": 66.44, "end": 66.8, "confidence": 0.929}, {"text": "such", "start": 66.8, "end": 67.22, "confidence": 1.0}, {"text": "a", "start": 67.22, "end": 67.44, "confidence": 1.0}, {"text": "fuckin'", "start": 67.44, "end": 68.3, "confidence": 0.993}, {"text": "hoe,", "start": 68.3, "end": 68.66, "confidence": 0.998}, {"text": "when", "start": 69.2, "end": 69.38, "confidence": 0.687}, {"text": "the", "start": 69.38, "end": 69.56, "confidence": 0.981}, {"text": "first", "start": 69.56, "end": 69.76, "confidence": 0.994}, {"text": "time", "start": 69.76, "end": 69.96, "confidence": 0.993}, {"text": "they", "start": 69.96, "end": 70.1, "confidence": 0.979}, {"text": "ask", "start": 70.1, "end": 70.32, "confidence": 0.666}, {"text": "you", "start": 70.32, "end": 70.43, "confidence": 0.931}]}, {"id": 12, "seek": 5700, "start": 70.43, "end": 71.86, "text": " You want sparkling or steel?", "tokens": [51026, 509, 528, 39967, 420, 8269, 30, 51106], "temperature": 0.0, "avg_logprob": -0.25641467923023664, "compression_ratio": 2.40251572327044, "no_speech_prob": 0.14192061126232147, "confidence": 0.662, "words": [{"text": "You", "start": 70.43, "end": 70.56, "confidence": 0.542}, {"text": "want", "start": 70.56, "end": 70.78, "confidence": 0.981}, {"text": "sparkling", "start": 70.78, "end": 71.26, "confidence": 0.426}, {"text": "or", "start": 71.26, "end": 71.6, "confidence": 0.979}, {"text": "steel?", "start": 71.6, "end": 71.86, "confidence": 0.571}]}, {"id": 13, "seek": 5700, "start": 71.96, "end": 73.85, "text": " Are you tryna act like you was drinkin' sparkling water", "tokens": [51106, 2014, 291, 49597, 605, 411, 291, 390, 2822, 259, 6, 39967, 1281, 51204], "temperature": 0.0, "avg_logprob": -0.25641467923023664, "compression_ratio": 2.40251572327044, "no_speech_prob": 0.14192061126232147, "confidence": 0.806, "words": [{"text": "Are", "start": 71.96, "end": 72.12, "confidence": 0.614}, {"text": "you", "start": 72.12, "end": 72.24, "confidence": 0.995}, {"text": "tryna", "start": 72.24, "end": 72.38, "confidence": 0.384}, {"text": "act", "start": 72.38, "end": 72.56, "confidence": 0.866}, {"text": "like", "start": 72.56, "end": 72.7, "confidence": 0.995}, {"text": "you", "start": 72.7, "end": 72.82, "confidence": 0.947}, {"text": "was", "start": 72.82, "end": 72.96, "confidence": 0.841}, {"text": "drinkin'", "start": 72.96, "end": 73.34, "confidence": 0.846}, {"text": "sparkling", "start": 73.34, "end": 73.62, "confidence": 0.788}, {"text": "water", "start": 73.62, "end": 73.85, "confidence": 0.976}]}, {"id": 14, "seek": 5700, "start": 73.85, "end": 74.74, "text": " Before you came out here?", "tokens": [51204, 4546, 291, 1361, 484, 510, 30, 51284], "temperature": 0.0, "avg_logprob": -0.25641467923023664, "compression_ratio": 2.40251572327044, "no_speech_prob": 0.14192061126232147, "confidence": 0.962, "words": [{"text": "Before", "start": 73.85, "end": 74.08, "confidence": 0.846}, {"text": "you", "start": 74.08, "end": 74.2, "confidence": 0.989}, {"text": "came", "start": 74.2, "end": 74.4, "confidence": 0.995}, {"text": "out", "start": 74.4, "end": 74.54, "confidence": 0.992}, {"text": "here?", "start": 74.54, "end": 74.74, "confidence": 0.996}]}, {"id": 15, "seek": 5700, "start": 75.68, "end": 79.26, "text": " You're such a fuckin' hoe, I'm a sick fuck, I like a quick fuck", "tokens": [51284, 509, 434, 1270, 257, 20022, 6, 19709, 11, 286, 478, 257, 4998, 3275, 11, 286, 411, 257, 1702, 3275, 51472], "temperature": 0.0, "avg_logprob": -0.25641467923023664, "compression_ratio": 2.40251572327044, "no_speech_prob": 0.14192061126232147, "confidence": 0.927, "words": [{"text": "You're", "start": 75.68, "end": 76.2, "confidence": 0.902}, {"text": "such", "start": 76.2, "end": 76.44, "confidence": 1.0}, {"text": "a", "start": 76.44, "end": 76.7, "confidence": 0.999}, {"text": "fuckin'", "start": 76.7, "end": 77.12, "confidence": 0.941}, {"text": "hoe,", "start": 77.12, "end": 77.3, "confidence": 0.668}, {"text": "I'm", "start": 77.3, "end": 77.5, "confidence": 0.978}, {"text": "a", "start": 77.5, "end": 77.64, "confidence": 0.721}, {"text": "sick", "start": 77.64, "end": 77.86, "confidence": 0.934}, {"text": "fuck,", "start": 77.86, "end": 78.12, "confidence": 0.991}, {"text": "I", "start": 78.22, "end": 78.32, "confidence": 0.981}, {"text": "like", "start": 78.32, "end": 78.56, "confidence": 0.994}, {"text": "a", "start": 78.56, "end": 78.76, "confidence": 0.955}, {"text": "quick", "start": 78.76, "end": 78.98, "confidence": 0.994}, {"text": "fuck", "start": 78.98, "end": 79.26, "confidence": 0.974}]}, {"id": 16, "seek": 5700, "start": 79.54, "end": 81.54, "text": " I'm a sick fuck, I like a quick fuck", "tokens": [51472, 286, 478, 257, 4998, 3275, 11, 286, 411, 257, 1702, 3275, 51584], "temperature": 0.0, "avg_logprob": -0.25641467923023664, "compression_ratio": 2.40251572327044, "no_speech_prob": 0.14192061126232147, "confidence": 0.987, "words": [{"text": "I'm", "start": 79.54, "end": 79.84, "confidence": 0.958}, {"text": "a", "start": 79.84, "end": 79.94, "confidence": 0.968}, {"text": "sick", "start": 79.94, "end": 80.16, "confidence": 0.999}, {"text": "fuck,", "start": 80.16, "end": 80.42, "confidence": 0.997}, {"text": "I", "start": 80.52, "end": 80.62, "confidence": 0.999}, {"text": "like", "start": 80.62, "end": 80.88, "confidence": 0.994}, {"text": "a", "start": 80.88, "end": 81.08, "confidence": 0.996}, {"text": "quick", "start": 81.08, "end": 81.26, "confidence": 0.999}, {"text": "fuck", "start": 81.26, "end": 81.54, "confidence": 0.998}]}, {"id": 17, "seek": 5700, "start": 81.86, "end": 83.84, "text": " I'm a sick fuck, I like a quick fuck", "tokens": [51584, 286, 478, 257, 4998, 3275, 11, 286, 411, 257, 1702, 3275, 51702], "temperature": 0.0, "avg_logprob": -0.25641467923023664, "compression_ratio": 2.40251572327044, "no_speech_prob": 0.14192061126232147, "confidence": 0.997, "words": [{"text": "I'm", "start": 81.86, "end": 82.12, "confidence": 0.992}, {"text": "a", "start": 82.12, "end": 82.26, "confidence": 0.995}, {"text": "sick", "start": 82.26, "end": 82.46, "confidence": 0.999}, {"text": "fuck,", "start": 82.46, "end": 82.72, "confidence": 0.998}, {"text": "I", "start": 82.84, "end": 82.92, "confidence": 1.0}, {"text": "like", "start": 82.92, "end": 83.18, "confidence": 0.999}, {"text": "a", "start": 83.18, "end": 83.4, "confidence": 0.998}, {"text": "quick", "start": 83.4, "end": 83.56, "confidence": 1.0}, {"text": "fuck", "start": 83.56, "end": 83.84, "confidence": 0.999}]}, {"id": 18, "seek": 5700, "start": 84.14, "end": 86.16, "text": " I'm a sick fuck, I like a quick fuck", "tokens": [51702, 286, 478, 257, 4998, 3275, 11, 286, 411, 257, 1702, 3275, 51816], "temperature": 0.0, "avg_logprob": -0.25641467923023664, "compression_ratio": 2.40251572327044, "no_speech_prob": 0.14192061126232147, "confidence": 0.963, "words": [{"text": "I'm", "start": 84.14, "end": 84.42, "confidence": 0.832}, {"text": "a", "start": 84.42, "end": 84.56, "confidence": 0.997}, {"text": "sick", "start": 84.56, "end": 84.78, "confidence": 0.999}, {"text": "fuck,", "start": 84.78, "end": 85.04, "confidence": 0.999}, {"text": "I", "start": 85.14, "end": 85.24, "confidence": 1.0}, {"text": "like", "start": 85.24, "end": 85.48, "confidence": 0.999}, {"text": "a", "start": 85.48, "end": 85.7, "confidence": 0.998}, {"text": "quick", "start": 85.7, "end": 85.88, "confidence": 0.999}, {"text": "fuck", "start": 85.88, "end": 86.16, "confidence": 0.999}]}, {"id": 19, "seek": 8604, "start": 86.18, "end": 88.46, "text": " I'm a sick fuck, I like a quick fuck", "tokens": [50366, 286, 478, 257, 4998, 3275, 11, 286, 411, 257, 1702, 3275, 50476], "temperature": 0.0, "avg_logprob": -0.22057748810062563, "compression_ratio": 1.8817733990147782, "no_speech_prob": 0.5832647681236267, "confidence": 0.989, "words": [{"text": "I'm", "start": 86.18, "end": 86.66, "confidence": 0.962}, {"text": "a", "start": 86.66, "end": 86.82, "confidence": 0.994}, {"text": "sick", "start": 86.82, "end": 87.08, "confidence": 0.998}, {"text": "fuck,", "start": 87.08, "end": 87.34, "confidence": 0.995}, {"text": "I", "start": 87.48, "end": 87.52, "confidence": 0.997}, {"text": "like", "start": 87.52, "end": 87.8, "confidence": 0.996}, {"text": "a", "start": 87.8, "end": 88.0, "confidence": 0.994}, {"text": "quick", "start": 88.0, "end": 88.22, "confidence": 0.999}, {"text": "fuck", "start": 88.22, "end": 88.46, "confidence": 0.998}]}, {"id": 20, "seek": 8604, "start": 88.54, "end": 90.74, "text": " I like my dick suck, I buy you a sick truck", "tokens": [50476, 286, 411, 452, 18659, 9967, 11, 286, 2256, 291, 257, 4998, 5898, 50592], "temperature": 0.0, "avg_logprob": -0.22057748810062563, "compression_ratio": 1.8817733990147782, "no_speech_prob": 0.5832647681236267, "confidence": 0.922, "words": [{"text": "I", "start": 88.54, "end": 88.68, "confidence": 0.997}, {"text": "like", "start": 88.68, "end": 88.9, "confidence": 0.987}, {"text": "my", "start": 88.9, "end": 89.12, "confidence": 0.984}, {"text": "dick", "start": 89.12, "end": 89.36, "confidence": 0.946}, {"text": "suck,", "start": 89.36, "end": 89.58, "confidence": 0.942}, {"text": "I", "start": 89.74, "end": 89.84, "confidence": 0.99}, {"text": "buy", "start": 89.84, "end": 89.98, "confidence": 0.521}, {"text": "you", "start": 89.98, "end": 90.14, "confidence": 0.998}, {"text": "a", "start": 90.14, "end": 90.28, "confidence": 0.996}, {"text": "sick", "start": 90.28, "end": 90.54, "confidence": 0.988}, {"text": "truck", "start": 90.54, "end": 90.74, "confidence": 0.936}]}, {"id": 21, "seek": 8604, "start": 90.84, "end": 93.02, "text": " I buy you some new tits, I get you the nip tuck", "tokens": [50592, 286, 2256, 291, 512, 777, 256, 1208, 11, 286, 483, 291, 264, 297, 647, 18457, 50706], "temperature": 0.0, "avg_logprob": -0.22057748810062563, "compression_ratio": 1.8817733990147782, "no_speech_prob": 0.5832647681236267, "confidence": 0.905, "words": [{"text": "I", "start": 90.84, "end": 90.98, "confidence": 0.995}, {"text": "buy", "start": 90.98, "end": 91.1, "confidence": 0.902}, {"text": "you", "start": 91.1, "end": 91.22, "confidence": 0.998}, {"text": "some", "start": 91.22, "end": 91.42, "confidence": 0.994}, {"text": "new", "start": 91.42, "end": 91.66, "confidence": 0.997}, {"text": "tits,", "start": 91.66, "end": 91.9, "confidence": 0.927}, {"text": "I", "start": 91.98, "end": 92.1, "confidence": 0.995}, {"text": "get", "start": 92.1, "end": 92.26, "confidence": 0.932}, {"text": "you", "start": 92.26, "end": 92.4, "confidence": 0.992}, {"text": "the", "start": 92.4, "end": 92.56, "confidence": 0.744}, {"text": "nip", "start": 92.56, "end": 92.84, "confidence": 0.912}, {"text": "tuck", "start": 92.84, "end": 93.02, "confidence": 0.571}]}, {"id": 22, "seek": 8604, "start": 93.28, "end": 95.36, "text": " How you start a family, the condom slipped up", "tokens": [50706, 1012, 291, 722, 257, 1605, 11, 264, 2224, 298, 28989, 493, 50822], "temperature": 0.0, "avg_logprob": -0.22057748810062563, "compression_ratio": 1.8817733990147782, "no_speech_prob": 0.5832647681236267, "confidence": 0.903, "words": [{"text": "How", "start": 93.28, "end": 93.48, "confidence": 0.982}, {"text": "you", "start": 93.48, "end": 93.64, "confidence": 0.958}, {"text": "start", "start": 93.64, "end": 93.84, "confidence": 0.959}, {"text": "a", "start": 93.84, "end": 94.02, "confidence": 0.994}, {"text": "family,", "start": 94.02, "end": 94.22, "confidence": 0.991}, {"text": "the", "start": 94.3, "end": 94.5, "confidence": 0.979}, {"text": "condom", "start": 94.5, "end": 94.8, "confidence": 0.754}, {"text": "slipped", "start": 94.8, "end": 95.16, "confidence": 0.73}, {"text": "up", "start": 95.16, "end": 95.36, "confidence": 0.997}]}, {"id": 23, "seek": 8604, "start": 95.66, "end": 97.6, "text": " I'm a sick fuck, I'm inappropriate", "tokens": [50822, 286, 478, 257, 4998, 3275, 11, 286, 478, 26723, 50936], "temperature": 0.0, "avg_logprob": -0.22057748810062563, "compression_ratio": 1.8817733990147782, "no_speech_prob": 0.5832647681236267, "confidence": 0.997, "words": [{"text": "I'm", "start": 95.66, "end": 95.92, "confidence": 0.999}, {"text": "a", "start": 95.92, "end": 96.08, "confidence": 0.996}, {"text": "sick", "start": 96.08, "end": 96.3, "confidence": 0.999}, {"text": "fuck,", "start": 96.3, "end": 96.54, "confidence": 0.999}, {"text": "I'm", "start": 96.72, "end": 96.92, "confidence": 0.999}, {"text": "inappropriate", "start": 96.92, "end": 97.6, "confidence": 0.986}]}, {"id": 24, "seek": 8604, "start": 97.82, "end": 99.94, "text": " I like hearing stories, I like that hoe shit", "tokens": [50936, 286, 411, 4763, 3676, 11, 286, 411, 300, 19709, 4611, 51054], "temperature": 0.0, "avg_logprob": -0.22057748810062563, "compression_ratio": 1.8817733990147782, "no_speech_prob": 0.5832647681236267, "confidence": 0.914, "words": [{"text": "I", "start": 97.82, "end": 97.88, "confidence": 0.989}, {"text": "like", "start": 97.88, "end": 98.26, "confidence": 0.998}, {"text": "hearing", "start": 98.26, "end": 98.54, "confidence": 0.733}, {"text": "stories,", "start": 98.54, "end": 98.9, "confidence": 0.998}, {"text": "I", "start": 98.98, "end": 99.1, "confidence": 0.998}, {"text": "like", "start": 99.1, "end": 99.3, "confidence": 0.998}, {"text": "that", "start": 99.3, "end": 99.52, "confidence": 0.996}, {"text": "hoe", "start": 99.52, "end": 99.74, "confidence": 0.624}, {"text": "shit", "start": 99.74, "end": 99.94, "confidence": 0.994}]}, {"id": 25, "seek": 8604, "start": 100.04, "end": 102.24, "text": " I wanna hear more shit, I like the hoe shit", "tokens": [51054, 286, 1948, 1568, 544, 4611, 11, 286, 411, 264, 19709, 4611, 51166], "temperature": 0.0, "avg_logprob": -0.22057748810062563, "compression_ratio": 1.8817733990147782, "no_speech_prob": 0.5832647681236267, "confidence": 0.9, "words": [{"text": "I", "start": 100.04, "end": 100.2, "confidence": 0.999}, {"text": "wanna", "start": 100.2, "end": 100.44, "confidence": 0.51}, {"text": "hear", "start": 100.44, "end": 100.7, "confidence": 0.955}, {"text": "more", "start": 100.7, "end": 100.88, "confidence": 0.834}, {"text": "shit,", "start": 100.88, "end": 101.14, "confidence": 0.998}, {"text": "I", "start": 101.26, "end": 101.4, "confidence": 0.999}, {"text": "like", "start": 101.4, "end": 101.62, "confidence": 0.997}, {"text": "the", "start": 101.62, "end": 101.84, "confidence": 0.975}, {"text": "hoe", "start": 101.84, "end": 102.0, "confidence": 0.886}, {"text": "shit", "start": 102.0, "end": 102.24, "confidence": 0.998}]}, {"id": 26, "seek": 8604, "start": 102.46, "end": 104.64, "text": " Send me some more shit, you trippin' hoe bitch", "tokens": [51166, 17908, 385, 512, 544, 4611, 11, 291, 1376, 427, 259, 6, 19709, 11960, 51296], "temperature": 0.0, "avg_logprob": -0.22057748810062563, "compression_ratio": 1.8817733990147782, "no_speech_prob": 0.5832647681236267, "confidence": 0.928, "words": [{"text": "Send", "start": 102.46, "end": 102.66, "confidence": 0.991}, {"text": "me", "start": 102.66, "end": 102.84, "confidence": 0.998}, {"text": "some", "start": 102.84, "end": 103.04, "confidence": 0.996}, {"text": "more", "start": 103.04, "end": 103.2, "confidence": 0.797}, {"text": "shit,", "start": 103.2, "end": 103.44, "confidence": 0.995}, {"text": "you", "start": 103.58, "end": 103.72, "confidence": 0.995}, {"text": "trippin'", "start": 103.72, "end": 104.28, "confidence": 0.914}, {"text": "hoe", "start": 104.28, "end": 104.38, "confidence": 0.946}, {"text": "bitch", "start": 104.38, "end": 104.64, "confidence": 0.794}]}, {"id": 27, "seek": 8604, "start": 104.64, "end": 110.04, "text": " You're such a fuckin' hoe, I love it", "tokens": [51296, 509, 434, 1270, 257, 20022, 6, 19709, 11, 286, 959, 309, 51736], "temperature": 0.0, "avg_logprob": -0.22057748810062563, "compression_ratio": 1.8817733990147782, "no_speech_prob": 0.5832647681236267, "confidence": 0.967, "words": [{"text": "You're", "start": 104.64, "end": 106.3, "confidence": 0.862}, {"text": "such", "start": 106.3, "end": 106.6, "confidence": 1.0}, {"text": "a", "start": 106.6, "end": 106.7, "confidence": 1.0}, {"text": "fuckin'", "start": 106.7, "end": 107.48, "confidence": 0.985}, {"text": "hoe,", "start": 107.48, "end": 107.7, "confidence": 0.996}, {"text": "I", "start": 108.16, "end": 108.38, "confidence": 0.999}, {"text": "love", "start": 108.38, "end": 108.74, "confidence": 0.999}, {"text": "it", "start": 108.74, "end": 110.04, "confidence": 1.0}]}, {"id": 28, "seek": 11348, "start": 114.14, "end": 116.3, "text": " You know they couldn't say the shit they wanted to say", "tokens": [50386, 509, 458, 436, 2809, 380, 584, 264, 4611, 436, 1415, 281, 584, 50526], "temperature": 0.0, "avg_logprob": -0.37552626927693683, "compression_ratio": 1.3035714285714286, "no_speech_prob": 0.7221440076828003, "confidence": 0.723, "words": [{"text": "You", "start": 114.14, "end": 114.32, "confidence": 0.365}, {"text": "know", "start": 114.32, "end": 114.5, "confidence": 0.732}, {"text": "they", "start": 114.5, "end": 114.86, "confidence": 0.245}, {"text": "couldn't", "start": 114.86, "end": 115.26, "confidence": 0.783}, {"text": "say", "start": 115.26, "end": 115.38, "confidence": 0.885}, {"text": "the", "start": 115.38, "end": 115.46, "confidence": 0.848}, {"text": "shit", "start": 115.46, "end": 115.56, "confidence": 0.993}, {"text": "they", "start": 115.56, "end": 115.7, "confidence": 0.944}, {"text": "wanted", "start": 115.7, "end": 115.92, "confidence": 0.834}, {"text": "to", "start": 115.92, "end": 116.1, "confidence": 0.962}, {"text": "say", "start": 116.1, "end": 116.3, "confidence": 0.9}]}, {"id": 29, "seek": 11348, "start": 116.96, "end": 118.82, "text": " They had the fake orgasms and shit", "tokens": [50526, 814, 632, 264, 7592, 44834, 2592, 293, 4611, 50636], "temperature": 0.0, "avg_logprob": -0.37552626927693683, "compression_ratio": 1.3035714285714286, "no_speech_prob": 0.7221440076828003, "confidence": 0.914, "words": [{"text": "They", "start": 116.96, "end": 117.1, "confidence": 0.971}, {"text": "had", "start": 117.1, "end": 117.26, "confidence": 0.973}, {"text": "the", "start": 117.26, "end": 117.48, "confidence": 0.557}, {"text": "fake", "start": 117.48, "end": 117.72, "confidence": 0.996}, {"text": "orgasms", "start": 117.72, "end": 118.36, "confidence": 0.983}, {"text": "and", "start": 118.36, "end": 118.56, "confidence": 0.968}, {"text": "shit", "start": 118.56, "end": 118.82, "confidence": 0.996}]}, {"id": 30, "seek": 11348, "start": 119.2, "end": 122.12, "text": " We can tell niggas today, hey, I wanna cum, motherfucker", "tokens": [50636, 492, 393, 980, 297, 6249, 296, 965, 11, 4177, 11, 286, 1948, 12713, 11, 47069, 50826], "temperature": 0.0, "avg_logprob": -0.37552626927693683, "compression_ratio": 1.3035714285714286, "no_speech_prob": 0.7221440076828003, "confidence": 0.944, "words": [{"text": "We", "start": 119.2, "end": 119.38, "confidence": 0.992}, {"text": "can", "start": 119.38, "end": 119.52, "confidence": 0.968}, {"text": "tell", "start": 119.52, "end": 119.74, "confidence": 0.996}, {"text": "niggas", "start": 119.74, "end": 120.0, "confidence": 0.958}, {"text": "today,", "start": 120.0, "end": 120.3, "confidence": 0.996}, {"text": "hey,", "start": 120.46, "end": 120.56, "confidence": 0.882}, {"text": "I", "start": 120.66, "end": 120.8, "confidence": 0.99}, {"text": "wanna", "start": 120.8, "end": 121.08, "confidence": 0.928}, {"text": "cum,", "start": 121.08, "end": 121.5, "confidence": 0.971}, {"text": "motherfucker", "start": 121.52, "end": 122.12, "confidence": 0.764}]}], "language": "en"}