{"text": " [\"Chartless Bike Man\"] Schau die die ist fucked von den drugs und sie has' Gas Ich hol' die Säuse ab, jetzt hab' schon Dreh' auf zwei Cups Sag' mir, ihr habt' Angst, doch ich will nur, dass die's haust Hör' dir gerne, dass wir reden, doch ich hab' zu viel Angst Schau die die ist fucked von den drugs und sie has' Gas Ich hol' die Säuse ab, jetzt hab' schon Dreh' auf zwei Cups Sag' mir, ihr habt' Angst, doch ich will nur, dass die's haust Hör' dir gerne, dass wir reden, doch ich hab' zu viel Angst Wegen den Homies will ich mich nicht loony Ich hol' zwei Charts und ich rumpf vor der Poly Sonst wird im Golfesend alles so fancy Sicht ist so dizzy, ich hauf' ich die Audi Oh fuck, ich nehm' einen Pants, bin nicht mehr wach Hau' bis du locker in dem Schlafst, ich hab' ein Paar noch gepasst Ich kehr' mit Brüdern im Park, ich zaufer' Dinge am Park Doch einem gefällt's egal, weil du mich jetzt nicht mehr machst Ich bin auch wach, pass auf dich, bin nur gefragt Von einem Shit, mann oder so, wie für die sich? Anzuklar, denk' nur an dich Oh fuck, ich zaufe, zu viel Angst Baby, ich bin fucked up, zu viel Joke Baby, ich hab' das Gas, komm und tu mich später ab Wir beide haben Angst, ich verdank' ein Bildernach Ich glaub', er will nur Spaß, doch er sagt es ja nicht mal Baby, ja sag' mir, was ist der Preis? Sieh' nur, ja sie machen Leben leiser", "segments": [{"id": 0, "seek": 0, "start": 0.22, "end": 29.6, "text": " [\"Chartless Bike Man\"]", "tokens": [50364, 29799, 6546, 446, 1832, 45699, 2458, 23711, 51856], "temperature": 0.0, "avg_logprob": -0.9554276899857954, "compression_ratio": 0.7333333333333333, "no_speech_prob": 0.22807765007019043, "confidence": 0.373, "words": [{"text": "[\"Chartless", "start": 0.22, "end": 14.68, "confidence": 0.272}, {"text": "Bike", "start": 14.68, "end": 14.98, "confidence": 0.69}, {"text": "Man\"]", "start": 14.98, "end": 29.6, "confidence": 0.711}]}, {"id": 1, "seek": 2984, "start": 30.06, "end": 33.4, "text": " Schau die die ist fucked von den drugs und sie has' Gas", "tokens": [50364, 2065, 1459, 978, 978, 1418, 22518, 2957, 1441, 7766, 674, 2804, 575, 6, 24025, 50544], "temperature": 0.0, "avg_logprob": -0.37058296686486353, "compression_ratio": 2.6871508379888267, "no_speech_prob": 0.8038982152938843, "confidence": 0.436, "words": [{"text": "Schau", "start": 30.06, "end": 30.48, "confidence": 0.332}, {"text": "die", "start": 30.48, "end": 30.68, "confidence": 0.365}, {"text": "die", "start": 30.68, "end": 30.84, "confidence": 0.305}, {"text": "ist", "start": 30.84, "end": 31.18, "confidence": 0.368}, {"text": "fucked", "start": 31.18, "end": 31.48, "confidence": 0.574}, {"text": "von", "start": 31.48, "end": 31.78, "confidence": 0.465}, {"text": "den", "start": 31.78, "end": 31.98, "confidence": 0.898}, {"text": "drugs", "start": 31.98, "end": 32.28, "confidence": 0.495}, {"text": "und", "start": 32.28, "end": 32.54, "confidence": 0.79}, {"text": "sie", "start": 32.54, "end": 32.74, "confidence": 0.926}, {"text": "has'", "start": 32.74, "end": 33.2, "confidence": 0.368}, {"text": "Gas", "start": 33.2, "end": 33.4, "confidence": 0.167}]}, {"id": 2, "seek": 2984, "start": 33.7, "end": 37.12, "text": " Ich hol' die Säuse ab, jetzt hab' schon Dreh' auf zwei Cups", "tokens": [50544, 3141, 4091, 6, 978, 318, 737, 438, 410, 11, 4354, 3025, 6, 4981, 413, 9017, 6, 2501, 12002, 383, 7528, 50734], "temperature": 0.0, "avg_logprob": -0.37058296686486353, "compression_ratio": 2.6871508379888267, "no_speech_prob": 0.8038982152938843, "confidence": 0.554, "words": [{"text": "Ich", "start": 33.7, "end": 33.96, "confidence": 0.455}, {"text": "hol'", "start": 33.96, "end": 34.14, "confidence": 0.848}, {"text": "die", "start": 34.14, "end": 34.32, "confidence": 0.688}, {"text": "Säuse", "start": 34.32, "end": 34.74, "confidence": 0.212}, {"text": "ab,", "start": 34.74, "end": 35.2, "confidence": 0.905}, {"text": "jetzt", "start": 35.4, "end": 35.56, "confidence": 0.346}, {"text": "hab'", "start": 35.56, "end": 35.74, "confidence": 0.525}, {"text": "schon", "start": 35.74, "end": 35.94, "confidence": 0.566}, {"text": "Dreh'", "start": 35.94, "end": 36.3, "confidence": 0.675}, {"text": "auf", "start": 36.3, "end": 36.44, "confidence": 0.736}, {"text": "zwei", "start": 36.44, "end": 36.7, "confidence": 0.846}, {"text": "Cups", "start": 36.7, "end": 37.12, "confidence": 0.811}]}, {"id": 3, "seek": 2984, "start": 37.6, "end": 40.86, "text": " Sag' mir, ihr habt' Angst, doch ich will nur, dass die's haust", "tokens": [50734, 34551, 6, 3149, 11, 5553, 23660, 6, 28622, 11, 9243, 1893, 486, 4343, 11, 2658, 978, 311, 324, 381, 50914], "temperature": 0.0, "avg_logprob": -0.37058296686486353, "compression_ratio": 2.6871508379888267, "no_speech_prob": 0.8038982152938843, "confidence": 0.49, "words": [{"text": "Sag'", "start": 37.6, "end": 37.9, "confidence": 0.441}, {"text": "mir,", "start": 37.9, "end": 38.12, "confidence": 0.943}, {"text": "ihr", "start": 38.12, "end": 38.42, "confidence": 0.373}, {"text": "habt'", "start": 38.42, "end": 38.72, "confidence": 0.302}, {"text": "Angst,", "start": 38.72, "end": 39.06, "confidence": 0.164}, {"text": "doch", "start": 39.18, "end": 39.32, "confidence": 0.849}, {"text": "ich", "start": 39.32, "end": 39.56, "confidence": 0.806}, {"text": "will", "start": 39.56, "end": 39.74, "confidence": 0.982}, {"text": "nur,", "start": 39.74, "end": 40.02, "confidence": 0.88}, {"text": "dass", "start": 40.2, "end": 40.22, "confidence": 0.981}, {"text": "die's", "start": 40.22, "end": 40.64, "confidence": 0.354}, {"text": "haust", "start": 40.64, "end": 40.86, "confidence": 0.385}]}, {"id": 4, "seek": 2984, "start": 40.94, "end": 44.64, "text": " Hör' dir gerne, dass wir reden, doch ich hab' zu viel Angst", "tokens": [50914, 389, 2311, 6, 4746, 15689, 11, 2658, 1987, 26447, 11, 9243, 1893, 3025, 6, 2164, 5891, 28622, 51114], "temperature": 0.0, "avg_logprob": -0.37058296686486353, "compression_ratio": 2.6871508379888267, "no_speech_prob": 0.8038982152938843, "confidence": 0.682, "words": [{"text": "Hör'", "start": 40.94, "end": 41.32, "confidence": 0.76}, {"text": "dir", "start": 41.32, "end": 41.38, "confidence": 0.467}, {"text": "gerne,", "start": 41.38, "end": 41.76, "confidence": 0.438}, {"text": "dass", "start": 41.88, "end": 42.08, "confidence": 0.228}, {"text": "wir", "start": 42.08, "end": 42.3, "confidence": 0.42}, {"text": "reden,", "start": 42.3, "end": 42.74, "confidence": 0.851}, {"text": "doch", "start": 42.8, "end": 43.06, "confidence": 0.937}, {"text": "ich", "start": 43.06, "end": 43.4, "confidence": 0.972}, {"text": "hab'", "start": 43.4, "end": 43.82, "confidence": 0.77}, {"text": "zu", "start": 43.82, "end": 43.96, "confidence": 0.871}, {"text": "viel", "start": 43.96, "end": 44.18, "confidence": 0.942}, {"text": "Angst", "start": 44.18, "end": 44.64, "confidence": 0.997}]}, {"id": 5, "seek": 2984, "start": 45.06, "end": 48.4, "text": " Schau die die ist fucked von den drugs und sie has' Gas", "tokens": [51114, 2065, 1459, 978, 978, 1418, 22518, 2957, 1441, 7766, 674, 2804, 575, 6, 24025, 51294], "temperature": 0.0, "avg_logprob": -0.37058296686486353, "compression_ratio": 2.6871508379888267, "no_speech_prob": 0.8038982152938843, "confidence": 0.974, "words": [{"text": "Schau", "start": 45.06, "end": 45.5, "confidence": 0.998}, {"text": "die", "start": 45.5, "end": 45.68, "confidence": 0.766}, {"text": "die", "start": 45.68, "end": 45.92, "confidence": 0.991}, {"text": "ist", "start": 45.92, "end": 46.16, "confidence": 0.993}, {"text": "fucked", "start": 46.16, "end": 46.48, "confidence": 0.997}, {"text": "von", "start": 46.48, "end": 46.8, "confidence": 0.994}, {"text": "den", "start": 46.8, "end": 46.98, "confidence": 0.999}, {"text": "drugs", "start": 46.98, "end": 47.28, "confidence": 0.999}, {"text": "und", "start": 47.28, "end": 47.54, "confidence": 0.981}, {"text": "sie", "start": 47.54, "end": 47.72, "confidence": 0.997}, {"text": "has'", "start": 47.72, "end": 48.18, "confidence": 0.986}, {"text": "Gas", "start": 48.18, "end": 48.4, "confidence": 0.977}]}, {"id": 6, "seek": 2984, "start": 48.7, "end": 52.14, "text": " Ich hol' die Säuse ab, jetzt hab' schon Dreh' auf zwei Cups", "tokens": [51294, 3141, 4091, 6, 978, 318, 737, 438, 410, 11, 4354, 3025, 6, 4981, 413, 9017, 6, 2501, 12002, 383, 7528, 51484], "temperature": 0.0, "avg_logprob": -0.37058296686486353, "compression_ratio": 2.6871508379888267, "no_speech_prob": 0.8038982152938843, "confidence": 0.991, "words": [{"text": "Ich", "start": 48.7, "end": 48.94, "confidence": 0.998}, {"text": "hol'", "start": 48.94, "end": 49.24, "confidence": 0.997}, {"text": "die", "start": 49.24, "end": 49.32, "confidence": 0.999}, {"text": "Säuse", "start": 49.32, "end": 49.78, "confidence": 0.998}, {"text": "ab,", "start": 49.78, "end": 50.22, "confidence": 0.997}, {"text": "jetzt", "start": 50.44, "end": 50.56, "confidence": 0.999}, {"text": "hab'", "start": 50.56, "end": 50.84, "confidence": 0.958}, {"text": "schon", "start": 50.84, "end": 50.96, "confidence": 0.988}, {"text": "Dreh'", "start": 50.96, "end": 51.3, "confidence": 0.999}, {"text": "auf", "start": 51.3, "end": 51.48, "confidence": 0.97}, {"text": "zwei", "start": 51.48, "end": 51.68, "confidence": 0.992}, {"text": "Cups", "start": 51.68, "end": 52.14, "confidence": 0.995}]}, {"id": 7, "seek": 2984, "start": 52.58, "end": 55.88, "text": " Sag' mir, ihr habt' Angst, doch ich will nur, dass die's haust", "tokens": [51484, 34551, 6, 3149, 11, 5553, 23660, 6, 28622, 11, 9243, 1893, 486, 4343, 11, 2658, 978, 311, 324, 381, 51664], "temperature": 0.0, "avg_logprob": -0.37058296686486353, "compression_ratio": 2.6871508379888267, "no_speech_prob": 0.8038982152938843, "confidence": 0.988, "words": [{"text": "Sag'", "start": 52.58, "end": 53.06, "confidence": 0.991}, {"text": "mir,", "start": 53.06, "end": 53.12, "confidence": 0.997}, {"text": "ihr", "start": 53.12, "end": 53.44, "confidence": 0.997}, {"text": "habt'", "start": 53.44, "end": 53.96, "confidence": 0.943}, {"text": "Angst,", "start": 53.96, "end": 54.0, "confidence": 0.982}, {"text": "doch", "start": 54.24, "end": 54.34, "confidence": 0.999}, {"text": "ich", "start": 54.34, "end": 54.56, "confidence": 0.999}, {"text": "will", "start": 54.56, "end": 54.76, "confidence": 0.999}, {"text": "nur,", "start": 54.76, "end": 54.98, "confidence": 0.999}, {"text": "dass", "start": 55.12, "end": 55.24, "confidence": 0.998}, {"text": "die's", "start": 55.24, "end": 55.64, "confidence": 0.989}, {"text": "haust", "start": 55.64, "end": 55.88, "confidence": 0.996}]}, {"id": 8, "seek": 2984, "start": 55.94, "end": 59.62, "text": " Hör' dir gerne, dass wir reden, doch ich hab' zu viel Angst", "tokens": [51664, 389, 2311, 6, 4746, 15689, 11, 2658, 1987, 26447, 11, 9243, 1893, 3025, 6, 2164, 5891, 28622, 51854], "temperature": 0.0, "avg_logprob": -0.37058296686486353, "compression_ratio": 2.6871508379888267, "no_speech_prob": 0.8038982152938843, "confidence": 0.95, "words": [{"text": "Hör'", "start": 55.94, "end": 56.26, "confidence": 0.96}, {"text": "dir", "start": 56.26, "end": 56.42, "confidence": 0.968}, {"text": "gerne,", "start": 56.42, "end": 56.76, "confidence": 0.959}, {"text": "dass", "start": 56.78, "end": 57.1, "confidence": 0.987}, {"text": "wir", "start": 57.1, "end": 57.28, "confidence": 1.0}, {"text": "reden,", "start": 57.28, "end": 57.68, "confidence": 0.999}, {"text": "doch", "start": 57.96, "end": 58.06, "confidence": 0.998}, {"text": "ich", "start": 58.06, "end": 58.38, "confidence": 0.999}, {"text": "hab'", "start": 58.38, "end": 58.8, "confidence": 0.763}, {"text": "zu", "start": 58.8, "end": 58.92, "confidence": 0.999}, {"text": "viel", "start": 58.92, "end": 59.18, "confidence": 0.995}, {"text": "Angst", "start": 59.18, "end": 59.62, "confidence": 0.999}]}, {"id": 9, "seek": 5964, "start": 59.64, "end": 61.5, "text": " Wegen den Homies will ich mich nicht loony", "tokens": [50364, 492, 1766, 1441, 20903, 530, 486, 1893, 6031, 1979, 450, 2526, 50464], "temperature": 0.0, "avg_logprob": -0.5364687799693582, "compression_ratio": 1.603125, "no_speech_prob": 0.47692397236824036, "confidence": 0.779, "words": [{"text": "Wegen", "start": 59.64, "end": 59.94, "confidence": 0.883}, {"text": "den", "start": 59.94, "end": 60.16, "confidence": 0.974}, {"text": "Homies", "start": 60.16, "end": 60.42, "confidence": 0.913}, {"text": "will", "start": 60.42, "end": 60.64, "confidence": 0.848}, {"text": "ich", "start": 60.64, "end": 60.76, "confidence": 0.97}, {"text": "mich", "start": 60.76, "end": 60.94, "confidence": 0.911}, {"text": "nicht", "start": 60.94, "end": 61.14, "confidence": 0.988}, {"text": "loony", "start": 61.14, "end": 61.5, "confidence": 0.371}]}, {"id": 10, "seek": 5964, "start": 61.56, "end": 63.3, "text": " Ich hol' zwei Charts und ich rumpf vor der Poly", "tokens": [50464, 3141, 4091, 6, 12002, 761, 11814, 674, 1893, 367, 1420, 69, 4245, 1163, 18553, 50554], "temperature": 0.0, "avg_logprob": -0.5364687799693582, "compression_ratio": 1.603125, "no_speech_prob": 0.47692397236824036, "confidence": 0.551, "words": [{"text": "Ich", "start": 61.56, "end": 61.72, "confidence": 0.899}, {"text": "hol'", "start": 61.72, "end": 61.86, "confidence": 0.555}, {"text": "zwei", "start": 61.86, "end": 61.96, "confidence": 0.901}, {"text": "Charts", "start": 61.96, "end": 62.2, "confidence": 0.447}, {"text": "und", "start": 62.2, "end": 62.38, "confidence": 0.719}, {"text": "ich", "start": 62.38, "end": 62.54, "confidence": 0.918}, {"text": "rumpf", "start": 62.54, "end": 62.62, "confidence": 0.358}, {"text": "vor", "start": 62.62, "end": 62.76, "confidence": 0.575}, {"text": "der", "start": 62.76, "end": 63.0, "confidence": 0.981}, {"text": "Poly", "start": 63.0, "end": 63.3, "confidence": 0.276}]}, {"id": 11, "seek": 5964, "start": 63.36, "end": 65.22, "text": " Sonst wird im Golfesend alles so fancy", "tokens": [50554, 318, 4068, 4578, 566, 30176, 279, 521, 7874, 370, 10247, 50644], "temperature": 0.0, "avg_logprob": -0.5364687799693582, "compression_ratio": 1.603125, "no_speech_prob": 0.47692397236824036, "confidence": 0.282, "words": [{"text": "Sonst", "start": 63.36, "end": 63.64, "confidence": 0.398}, {"text": "wird", "start": 63.64, "end": 63.74, "confidence": 0.176}, {"text": "im", "start": 63.74, "end": 63.9, "confidence": 0.189}, {"text": "Golfesend", "start": 63.9, "end": 64.46, "confidence": 0.205}, {"text": "alles", "start": 64.46, "end": 64.62, "confidence": 0.365}, {"text": "so", "start": 64.62, "end": 64.92, "confidence": 0.354}, {"text": "fancy", "start": 64.92, "end": 65.22, "confidence": 0.537}]}, {"id": 12, "seek": 5964, "start": 65.26, "end": 67.08, "text": " Sicht ist so dizzy, ich hauf' ich die Audi", "tokens": [50644, 36615, 1418, 370, 31098, 11, 1893, 324, 2947, 6, 1893, 978, 28943, 50744], "temperature": 0.0, "avg_logprob": -0.5364687799693582, "compression_ratio": 1.603125, "no_speech_prob": 0.47692397236824036, "confidence": 0.589, "words": [{"text": "Sicht", "start": 65.26, "end": 65.48, "confidence": 0.187}, {"text": "ist", "start": 65.48, "end": 65.68, "confidence": 0.65}, {"text": "so", "start": 65.68, "end": 65.86, "confidence": 0.939}, {"text": "dizzy,", "start": 65.86, "end": 66.08, "confidence": 0.686}, {"text": "ich", "start": 66.2, "end": 66.28, "confidence": 0.986}, {"text": "hauf'", "start": 66.28, "end": 66.5, "confidence": 0.471}, {"text": "ich", "start": 66.5, "end": 66.6, "confidence": 0.91}, {"text": "die", "start": 66.6, "end": 66.76, "confidence": 0.408}, {"text": "Audi", "start": 66.76, "end": 67.08, "confidence": 0.978}]}, {"id": 13, "seek": 5964, "start": 67.18, "end": 70.64, "text": " Oh fuck, ich nehm' einen Pants, bin nicht mehr wach", "tokens": [50744, 876, 3275, 11, 1893, 408, 8587, 6, 4891, 430, 1719, 11, 5171, 1979, 5417, 261, 608, 50924], "temperature": 0.0, "avg_logprob": -0.5364687799693582, "compression_ratio": 1.603125, "no_speech_prob": 0.47692397236824036, "confidence": 0.564, "words": [{"text": "Oh", "start": 67.18, "end": 67.72, "confidence": 0.685}, {"text": "fuck,", "start": 67.72, "end": 68.0, "confidence": 0.542}, {"text": "ich", "start": 68.12, "end": 68.36, "confidence": 0.83}, {"text": "nehm'", "start": 68.36, "end": 68.6, "confidence": 0.803}, {"text": "einen", "start": 68.6, "end": 68.94, "confidence": 0.225}, {"text": "Pants,", "start": 68.94, "end": 69.4, "confidence": 0.137}, {"text": "bin", "start": 69.52, "end": 69.7, "confidence": 0.963}, {"text": "nicht", "start": 69.7, "end": 70.02, "confidence": 0.523}, {"text": "mehr", "start": 70.02, "end": 70.26, "confidence": 0.992}, {"text": "wach", "start": 70.26, "end": 70.64, "confidence": 0.99}]}, {"id": 14, "seek": 5964, "start": 70.86, "end": 74.36, "text": " Hau' bis du locker in dem Schlafst, ich hab' ein Paar noch gepasst", "tokens": [50924, 389, 1459, 6, 7393, 1581, 25707, 294, 1371, 2065, 33037, 372, 11, 1893, 3025, 6, 1343, 3426, 289, 3514, 30979, 48435, 51104], "temperature": 0.0, "avg_logprob": -0.5364687799693582, "compression_ratio": 1.603125, "no_speech_prob": 0.47692397236824036, "confidence": 0.567, "words": [{"text": "Hau'", "start": 70.86, "end": 71.24, "confidence": 0.4}, {"text": "bis", "start": 71.24, "end": 71.4, "confidence": 0.73}, {"text": "du", "start": 71.4, "end": 71.5, "confidence": 0.737}, {"text": "locker", "start": 71.5, "end": 71.78, "confidence": 0.134}, {"text": "in", "start": 71.78, "end": 71.92, "confidence": 0.212}, {"text": "dem", "start": 71.92, "end": 72.06, "confidence": 0.284}, {"text": "Schlafst,", "start": 72.06, "end": 72.6, "confidence": 0.788}, {"text": "ich", "start": 72.74, "end": 72.88, "confidence": 0.989}, {"text": "hab'", "start": 72.88, "end": 73.18, "confidence": 0.983}, {"text": "ein", "start": 73.18, "end": 73.36, "confidence": 0.831}, {"text": "Paar", "start": 73.36, "end": 73.5, "confidence": 0.765}, {"text": "noch", "start": 73.5, "end": 73.76, "confidence": 0.946}, {"text": "gepasst", "start": 73.76, "end": 74.36, "confidence": 0.442}]}, {"id": 15, "seek": 5964, "start": 74.38, "end": 78.12, "text": " Ich kehr' mit Brüdern im Park, ich zaufer' Dinge am Park", "tokens": [51104, 3141, 803, 1703, 6, 2194, 1603, 774, 35520, 566, 4964, 11, 1893, 710, 1459, 612, 6, 25102, 669, 4964, 51304], "temperature": 0.0, "avg_logprob": -0.5364687799693582, "compression_ratio": 1.603125, "no_speech_prob": 0.47692397236824036, "confidence": 0.649, "words": [{"text": "Ich", "start": 74.38, "end": 74.72, "confidence": 0.737}, {"text": "kehr'", "start": 74.72, "end": 75.1, "confidence": 0.496}, {"text": "mit", "start": 75.1, "end": 75.14, "confidence": 0.977}, {"text": "Brüdern", "start": 75.14, "end": 75.62, "confidence": 0.898}, {"text": "im", "start": 75.62, "end": 75.9, "confidence": 0.54}, {"text": "Park,", "start": 75.9, "end": 76.24, "confidence": 0.983}, {"text": "ich", "start": 76.4, "end": 76.62, "confidence": 0.52}, {"text": "zaufer'", "start": 76.62, "end": 77.02, "confidence": 0.624}, {"text": "Dinge", "start": 77.02, "end": 77.44, "confidence": 0.321}, {"text": "am", "start": 77.44, "end": 77.82, "confidence": 0.55}, {"text": "Park", "start": 77.82, "end": 78.12, "confidence": 0.887}]}, {"id": 16, "seek": 5964, "start": 78.42, "end": 81.88, "text": " Doch einem gefällt's egal, weil du mich jetzt nicht mehr machst", "tokens": [51304, 21533, 6827, 11271, 25333, 311, 31528, 11, 7689, 1581, 6031, 4354, 1979, 5417, 43350, 51484], "temperature": 0.0, "avg_logprob": -0.5364687799693582, "compression_ratio": 1.603125, "no_speech_prob": 0.47692397236824036, "confidence": 0.758, "words": [{"text": "Doch", "start": 78.42, "end": 78.74, "confidence": 0.984}, {"text": "einem", "start": 78.74, "end": 79.1, "confidence": 0.302}, {"text": "gefällt's", "start": 79.1, "end": 79.82, "confidence": 0.479}, {"text": "egal,", "start": 79.82, "end": 80.0, "confidence": 0.979}, {"text": "weil", "start": 80.16, "end": 80.28, "confidence": 0.979}, {"text": "du", "start": 80.28, "end": 80.52, "confidence": 0.992}, {"text": "mich", "start": 80.52, "end": 80.78, "confidence": 0.985}, {"text": "jetzt", "start": 80.78, "end": 81.02, "confidence": 0.929}, {"text": "nicht", "start": 81.02, "end": 81.28, "confidence": 0.977}, {"text": "mehr", "start": 81.28, "end": 81.5, "confidence": 0.997}, {"text": "machst", "start": 81.5, "end": 81.88, "confidence": 0.991}]}, {"id": 17, "seek": 5964, "start": 82.1, "end": 84.88, "text": " Ich bin auch wach, pass auf dich, bin nur gefragt", "tokens": [51484, 3141, 5171, 2168, 261, 608, 11, 1320, 2501, 10390, 11, 5171, 4343, 11271, 32243, 51634], "temperature": 0.0, "avg_logprob": -0.5364687799693582, "compression_ratio": 1.603125, "no_speech_prob": 0.47692397236824036, "confidence": 0.611, "words": [{"text": "Ich", "start": 82.1, "end": 82.32, "confidence": 0.991}, {"text": "bin", "start": 82.32, "end": 82.5, "confidence": 0.998}, {"text": "auch", "start": 82.5, "end": 82.76, "confidence": 0.595}, {"text": "wach,", "start": 82.76, "end": 83.04, "confidence": 0.994}, {"text": "pass", "start": 83.18, "end": 83.38, "confidence": 0.512}, {"text": "auf", "start": 83.38, "end": 83.6, "confidence": 0.953}, {"text": "dich,", "start": 83.6, "end": 83.96, "confidence": 0.986}, {"text": "bin", "start": 84.06, "end": 84.22, "confidence": 0.375}, {"text": "nur", "start": 84.22, "end": 84.36, "confidence": 0.819}, {"text": "gefragt", "start": 84.36, "end": 84.88, "confidence": 0.178}]}, {"id": 18, "seek": 5964, "start": 84.92, "end": 87.72, "text": " Von einem Shit, mann oder so, wie für die sich?", "tokens": [51634, 20700, 6827, 19593, 11, 587, 77, 4513, 370, 11, 3355, 2959, 978, 3041, 30, 51774], "temperature": 0.0, "avg_logprob": -0.5364687799693582, "compression_ratio": 1.603125, "no_speech_prob": 0.47692397236824036, "confidence": 0.339, "words": [{"text": "Von", "start": 84.92, "end": 85.16, "confidence": 0.279}, {"text": "einem", "start": 85.16, "end": 85.38, "confidence": 0.396}, {"text": "Shit,", "start": 85.38, "end": 85.8, "confidence": 0.776}, {"text": "mann", "start": 85.92, "end": 86.26, "confidence": 0.103}, {"text": "oder", "start": 86.26, "end": 86.36, "confidence": 0.126}, {"text": "so,", "start": 86.36, "end": 86.7, "confidence": 0.27}, {"text": "wie", "start": 86.82, "end": 87.02, "confidence": 0.477}, {"text": "für", "start": 87.02, "end": 87.2, "confidence": 0.794}, {"text": "die", "start": 87.2, "end": 87.36, "confidence": 0.823}, {"text": "sich?", "start": 87.36, "end": 87.72, "confidence": 0.689}]}, {"id": 19, "seek": 8784, "start": 87.84, "end": 89.66, "text": " Anzuklar, denk' nur an dich", "tokens": [50364, 1107, 89, 2034, 2200, 11, 21285, 6, 4343, 364, 10390, 50464], "temperature": 0.0, "avg_logprob": -0.7640055876511794, "compression_ratio": 0.7714285714285715, "no_speech_prob": 0.9185137748718262, "confidence": 0.441, "words": [{"text": "Anzuklar,", "start": 87.84, "end": 88.66, "confidence": 0.246}, {"text": "denk'", "start": 88.82, "end": 89.18, "confidence": 0.574}, {"text": "nur", "start": 89.18, "end": 89.2, "confidence": 0.541}, {"text": "an", "start": 89.2, "end": 89.36, "confidence": 0.983}, {"text": "dich", "start": 89.36, "end": 89.66, "confidence": 0.996}]}, {"id": 20, "seek": 11784, "start": 117.84, "end": 119.7, "text": " Oh fuck, ich zaufe, zu viel Angst", "tokens": [50364, 876, 3275, 11, 1893, 710, 1459, 2106, 11, 2164, 5891, 28622, 50464], "temperature": 0.0, "avg_logprob": -0.23107181429328405, "compression_ratio": 2.708542713567839, "no_speech_prob": 0.9142754673957825, "confidence": 0.646, "words": [{"text": "Oh", "start": 117.84, "end": 118.12, "confidence": 0.291}, {"text": "fuck,", "start": 118.12, "end": 118.36, "confidence": 0.407}, {"text": "ich", "start": 118.38, "end": 118.4, "confidence": 0.924}, {"text": "zaufe,", "start": 118.4, "end": 118.66, "confidence": 0.679}, {"text": "zu", "start": 118.74, "end": 118.94, "confidence": 0.607}, {"text": "viel", "start": 118.94, "end": 119.16, "confidence": 0.951}, {"text": "Angst", "start": 119.16, "end": 119.7, "confidence": 0.997}]}, {"id": 21, "seek": 11784, "start": 120.1, "end": 123.42, "text": " Baby, ich bin fucked up, zu viel Joke", "tokens": [50464, 9425, 11, 1893, 5171, 22518, 493, 11, 2164, 5891, 508, 2949, 50664], "temperature": 0.0, "avg_logprob": -0.23107181429328405, "compression_ratio": 2.708542713567839, "no_speech_prob": 0.9142754673957825, "confidence": 0.76, "words": [{"text": "Baby,", "start": 120.1, "end": 120.5, "confidence": 0.983}, {"text": "ich", "start": 120.66, "end": 120.8, "confidence": 0.989}, {"text": "bin", "start": 120.8, "end": 121.1, "confidence": 0.998}, {"text": "fucked", "start": 121.1, "end": 121.62, "confidence": 0.938}, {"text": "up,", "start": 121.62, "end": 122.12, "confidence": 0.975}, {"text": "zu", "start": 122.56, "end": 122.68, "confidence": 0.911}, {"text": "viel", "start": 122.68, "end": 122.96, "confidence": 0.962}, {"text": "Joke", "start": 122.96, "end": 123.42, "confidence": 0.33}]}, {"id": 22, "seek": 11784, "start": 123.82, "end": 127.04, "text": " Baby, ich hab' das Gas, komm und tu mich später ab", "tokens": [50664, 9425, 11, 1893, 3025, 6, 1482, 24025, 11, 6669, 674, 2604, 6031, 24196, 410, 50814], "temperature": 0.0, "avg_logprob": -0.23107181429328405, "compression_ratio": 2.708542713567839, "no_speech_prob": 0.9142754673957825, "confidence": 0.734, "words": [{"text": "Baby,", "start": 123.82, "end": 124.24, "confidence": 0.985}, {"text": "ich", "start": 124.3, "end": 124.52, "confidence": 0.978}, {"text": "hab'", "start": 124.52, "end": 124.64, "confidence": 0.843}, {"text": "das", "start": 124.64, "end": 124.88, "confidence": 0.361}, {"text": "Gas,", "start": 124.88, "end": 125.22, "confidence": 0.644}, {"text": "komm", "start": 125.44, "end": 125.56, "confidence": 0.945}, {"text": "und", "start": 125.56, "end": 125.8, "confidence": 0.399}, {"text": "tu", "start": 125.8, "end": 126.0, "confidence": 0.792}, {"text": "mich", "start": 126.0, "end": 126.2, "confidence": 0.534}, {"text": "später", "start": 126.2, "end": 126.62, "confidence": 0.975}, {"text": "ab", "start": 126.62, "end": 127.04, "confidence": 0.992}]}, {"id": 23, "seek": 11784, "start": 127.42, "end": 130.82, "text": " Wir beide haben Angst, ich verdank' ein Bildernach", "tokens": [50814, 4347, 35831, 3084, 28622, 11, 1893, 6387, 657, 6, 1343, 15746, 1248, 608, 51014], "temperature": 0.0, "avg_logprob": -0.23107181429328405, "compression_ratio": 2.708542713567839, "no_speech_prob": 0.9142754673957825, "confidence": 0.516, "words": [{"text": "Wir", "start": 127.42, "end": 127.72, "confidence": 0.76}, {"text": "beide", "start": 127.72, "end": 128.12, "confidence": 0.993}, {"text": "haben", "start": 128.12, "end": 128.5, "confidence": 0.946}, {"text": "Angst,", "start": 128.5, "end": 128.98, "confidence": 0.998}, {"text": "ich", "start": 129.2, "end": 129.3, "confidence": 0.984}, {"text": "verdank'", "start": 129.3, "end": 129.86, "confidence": 0.379}, {"text": "ein", "start": 129.86, "end": 130.06, "confidence": 0.234}, {"text": "Bildernach", "start": 130.06, "end": 130.82, "confidence": 0.342}]}, {"id": 24, "seek": 11784, "start": 131.12, "end": 134.58, "text": " Ich glaub', er will nur Spaß, doch er sagt es ja nicht mal", "tokens": [51014, 3141, 23210, 6098, 1189, 486, 4343, 27460, 11, 9243, 1189, 15764, 785, 2784, 1979, 2806, 51214], "temperature": 0.0, "avg_logprob": -0.23107181429328405, "compression_ratio": 2.708542713567839, "no_speech_prob": 0.9142754673957825, "confidence": 0.897, "words": [{"text": "Ich", "start": 131.12, "end": 131.36, "confidence": 0.997}, {"text": "glaub',", "start": 131.36, "end": 131.74, "confidence": 0.974}, {"text": "er", "start": 131.74, "end": 131.9, "confidence": 0.984}, {"text": "will", "start": 131.9, "end": 132.06, "confidence": 0.959}, {"text": "nur", "start": 132.06, "end": 132.32, "confidence": 0.985}, {"text": "Spaß,", "start": 132.32, "end": 132.72, "confidence": 0.986}, {"text": "doch", "start": 132.82, "end": 133.04, "confidence": 0.996}, {"text": "er", "start": 133.04, "end": 133.32, "confidence": 0.992}, {"text": "sagt", "start": 133.32, "end": 133.56, "confidence": 0.962}, {"text": "es", "start": 133.56, "end": 133.84, "confidence": 0.492}, {"text": "ja", "start": 133.84, "end": 133.98, "confidence": 0.908}, {"text": "nicht", "start": 133.98, "end": 134.24, "confidence": 0.97}, {"text": "mal", "start": 134.24, "end": 134.58, "confidence": 0.661}]}, {"id": 25, "seek": 11784, "start": 135.14, "end": 137.44, "text": " Baby, ja sag' mir, was ist der Preis?", "tokens": [51214, 9425, 11, 2784, 15274, 6, 3149, 11, 390, 1418, 1163, 47042, 30, 51364], "temperature": 0.0, "avg_logprob": -0.23107181429328405, "compression_ratio": 2.708542713567839, "no_speech_prob": 0.9142754673957825, "confidence": 0.901, "words": [{"text": "Baby,", "start": 135.14, "end": 135.56, "confidence": 0.995}, {"text": "ja", "start": 135.7, "end": 135.88, "confidence": 0.625}, {"text": "sag'", "start": 135.88, "end": 136.14, "confidence": 0.806}, {"text": "mir,", "start": 136.14, "end": 136.28, "confidence": 0.998}, {"text": "was", "start": 136.46, "end": 136.6, "confidence": 0.994}, {"text": "ist", "start": 136.6, "end": 136.8, "confidence": 0.987}, {"text": "der", "start": 136.8, "end": 136.98, "confidence": 0.995}, {"text": "Preis?", "start": 136.98, "end": 137.44, "confidence": 0.998}]}, {"id": 26, "seek": 13784, "start": 138.88, "end": 141.42, "text": " Sieh' nur, ja sie machen Leben leiser", "tokens": [50414, 3559, 71, 6, 4343, 11, 2784, 2804, 7069, 15399, 476, 6694, 50564], "temperature": 0.0, "avg_logprob": -0.8754785401480538, "compression_ratio": 0.8604651162790697, "no_speech_prob": 0.9021828770637512, "confidence": 0.357, "words": [{"text": "Sieh'", "start": 138.88, "end": 139.26, "confidence": 0.225}, {"text": "nur,", "start": 139.26, "end": 139.4, "confidence": 0.215}, {"text": "ja", "start": 139.54, "end": 139.64, "confidence": 0.623}, {"text": "sie", "start": 139.64, "end": 139.78, "confidence": 0.903}, {"text": "machen", "start": 139.78, "end": 140.22, "confidence": 0.535}, {"text": "Leben", "start": 140.22, "end": 140.76, "confidence": 0.791}, {"text": "leiser", "start": 140.76, "end": 141.42, "confidence": 0.241}]}], "language": "EN"}